qhub/__init__.py
qhub/__main__.py
qhub/_version.py
qhub/constants.py
qhub/cost.py
qhub/deploy.py
qhub/deprecate.py
qhub/destroy.py
qhub/initialize.py
qhub/keycloak.py
qhub/render.py
qhub/schema.py
qhub/upgrade.py
qhub/utils.py
qhub/version.py
qhub/cli/__init__.py
qhub/cli/_init.py
qhub/cli/_keycloak.py
qhub/cli/cost.py
qhub/cli/deploy.py
qhub/cli/destroy.py
qhub/cli/initialize.py
qhub/cli/keycloak.py
qhub/cli/main.py
qhub/cli/render.py
qhub/cli/support.py
qhub/cli/upgrade.py
qhub/cli/validate.py
qhub/provider/__init__.py
qhub/provider/git.py
qhub/provider/terraform.py
qhub/provider/cicd/__init__.py
qhub/provider/cicd/common.py
qhub/provider/cicd/github.py
qhub/provider/cicd/gitlab.py
qhub/provider/cicd/linter.py
qhub/provider/cloud/__init__.py
qhub/provider/cloud/amazon_web_services.py
qhub/provider/cloud/azure_cloud.py
qhub/provider/cloud/commons.py
qhub/provider/cloud/digital_ocean.py
qhub/provider/cloud/google_cloud.py
qhub/provider/dns/__init__.py
qhub/provider/dns/cloudflare.py
qhub/provider/oauth/__init__.py
qhub/provider/oauth/auth0.py
qhub/stages/__init__.py
qhub/stages/checks.py
qhub/stages/input_vars.py
qhub/stages/state_imports.py
qhub/stages/tf_objects.py
qhub/template/stages/01-terraform-state/aws/main.tf
qhub/template/stages/01-terraform-state/aws/modules/terraform-state/main.tf
qhub/template/stages/01-terraform-state/aws/modules/terraform-state/output.tf
qhub/template/stages/01-terraform-state/aws/modules/terraform-state/variables.tf
qhub/template/stages/01-terraform-state/azure/main.tf
qhub/template/stages/01-terraform-state/azure/modules/terraform-state/main.tf
qhub/template/stages/01-terraform-state/azure/modules/terraform-state/variables.tf
qhub/template/stages/01-terraform-state/do/main.tf
qhub/template/stages/01-terraform-state/do/modules/spaces/main.tf
qhub/template/stages/01-terraform-state/do/modules/spaces/variables.tf
qhub/template/stages/01-terraform-state/do/modules/spaces/versions.tf
qhub-0.4.5.dist-info/LICENSE
qhub-0.4.5.dist-info/METADATA
qhub-0.4.5.dist-info/WHEEL
qhub-0.4.5.dist-info/entry_points.txt
qhub-0.4.5.dist-info/top_level.txt
qhub-0.4.5.dist-info/RECORD
