Metadata-Version: 2.1
Name: qhub
Version: 0.4.5
Summary: Management of QHub on Cloud Infrastructure
Home-page: https://github.com/quansight/qhub
Author: Quansight
License: BSD 3-Clause License
Project-URL: Bug Reports, https://github.com/quansight/qhub/issues
Project-URL: Source, https://github.com/quansight/qhub
Keywords: aws,gcp,do,azure,qhub
Classifier: Development Status :: 3 - Alpha
Classifier: Intended Audience :: Developers
Classifier: Topic :: Software Development :: Build Tools
Classifier: Programming Language :: Python :: 3
Classifier: Programming Language :: Python :: 3.7
Classifier: Programming Language :: Python :: 3.8
Classifier: Programming Language :: Python :: 3.9
Classifier: Programming Language :: Python :: 3.10
License-File: LICENSE
Requires-Dist: ruamel.yaml
Requires-Dist: cloudflare
Requires-Dist: auth0-python
Requires-Dist: pydantic
Requires-Dist: pynacl
Requires-Dist: bcrypt
Requires-Dist: kubernetes
Requires-Dist: azure-identity (==1.6.1)
Requires-Dist: azure-mgmt-containerservice (==16.2.0)
Requires-Dist: boto3
Requires-Dist: python-keycloak
Requires-Dist: rich
Requires-Dist: typer
Requires-Dist: questionary
Requires-Dist: importlib-metadata ; python_version < "3.8"
Provides-Extra: dev
Requires-Dist: flake8 (==3.8.4) ; extra == 'dev'
Requires-Dist: black (==22.3.0) ; extra == 'dev'
Requires-Dist: importlib-metadata (<5.0) ; extra == 'dev'
Requires-Dist: twine ; extra == 'dev'
Requires-Dist: pytest ; extra == 'dev'
Requires-Dist: pytest-timeout ; extra == 'dev'
Requires-Dist: diagrams ; extra == 'dev'
Requires-Dist: jhub-client ; extra == 'dev'
Requires-Dist: pre-commit ; extra == 'dev'
Requires-Dist: kubernetes ; extra == 'dev'
Requires-Dist: dask-gateway ; extra == 'dev'
Requires-Dist: paramiko ; extra == 'dev'
Requires-Dist: escapism ; extra == 'dev'
